{
    "tex-preload.map": {
        "modified": "2006-03-04 03:55:34",
        "size": "286.51KB",
        "md5": "c4f80da57c6a7b83558138bcffb86cb4",
        "sha256": "be1de4fe8ff23e0e8c760913a7946ada18eca21c5299bb84744f1f2efcdbcd46"
    },
    "Metadata": {
        "Content-Encoding": "windows-1252",
        "Content-Type": "text/plain; charset=windows-1252",
        "X-Parsed-By": [
            "org.apache.tika.parser.DefaultParser",
            "org.apache.tika.parser.csv.TextAndCSVParser"
        ],
        "X-TIKA:content_handler": "ToTextContentHandler",
        "X-TIKA:embedded_depth": "0",
        "X-TIKA:parse_time_millis": "2",
        "resourceName": "b'tex-preload.map'"
    }
}