{
    "Jyasinzou_OLD(ver2)_ROOM14.o": {
        "modified": "2020-10-06 13:39:42.170663",
        "size": "24.39KB",
        "md5": "be9dd3a8f29c46e28dc30842a73655f8",
        "sha256": "6b2622e8d52aa380b510a2febe47a5b470e1a6b5d0c27a8e952fbe11995b91b9"
    },
    "Metadata": {
        "Content-Type": "application/x-object",
        "X-Parsed-By": [
            "org.apache.tika.parser.DefaultParser",
            "org.apache.tika.parser.executable.ExecutableParser"
        ],
        "X-TIKA:embedded_depth": "0",
        "X-TIKA:parse_time_millis": "0",
        "machine:architectureBits": "32",
        "machine:endian": "Big",
        "machine:machineType": "MIPS",
        "resourceName": "b'Jyasinzou_OLD(ver2)_ROOM14.o'"
    }
}