{
    "Kokiri.bak_SCENE.o": {
        "modified": "2020-10-06 13:39:42.221663",
        "size": "4.93KB",
        "md5": "a6cd672e167bdafb059bccbfefb98369",
        "sha256": "483bfd1b53278efd1bcb11b78f0620dc1423dd059d4e8916ad0cee92539ea229"
    },
    "Metadata": {
        "Content-Type": "application/x-object",
        "X-Parsed-By": [
            "org.apache.tika.parser.DefaultParser",
            "org.apache.tika.parser.executable.ExecutableParser"
        ],
        "X-TIKA:embedded_depth": "0",
        "X-TIKA:parse_time_millis": "0",
        "machine:architectureBits": "32",
        "machine:endian": "Big",
        "machine:machineType": "MIPS",
        "resourceName": "b'Kokiri.bak_SCENE.o'"
    }
}