{
    "OpenSystemEditorAction.html": {
        "modified": "2006-01-18 15:24:52",
        "size": "27.14KB",
        "md5": "54b50b6b1a7d3c390154342cd82fe97c",
        "sha256": "7664acaf3660e2f64654a35bf9aacbb99c9408693e35aab57931e6872c48d6e3"
    },
    "Metadata": {
        "Content-Encoding": "ISO-8859-1",
        "Content-Type": "text/html; charset=ISO-8859-1",
        "Content-Type-Hint": "text/html; charset=iso-8859-1",
        "X-Parsed-By": [
            "org.apache.tika.parser.DefaultParser",
            "org.apache.tika.parser.html.HtmlParser"
        ],
        "X-TIKA:content_handler": "ToTextContentHandler",
        "X-TIKA:embedded_depth": "0",
        "X-TIKA:parse_time_millis": "3",
        "dc:title": "OpenSystemEditorAction (Eclipse Platform API Specification)",
        "keywords": "org.eclipse.ui.actions.OpenSystemEditorAction class",
        "resourceName": "b'OpenSystemEditorAction.html'",
        "title": "OpenSystemEditorAction (Eclipse Platform API Specification)"
    }
}