{
    "devreqst.c": {
        "modified": "2020-10-06 13:42:11.245030",
        "size": "4.83KB",
        "md5": "a685782e3c5b034102fee48d0b3a2c91",
        "sha256": "4d38f18980c7745ac575be272b5d85ced58de57432576f581d84072ac95a86ae"
    },
    "Metadata": {
        "Content-Encoding": "windows-1252",
        "Content-Type": "text/plain; charset=windows-1252",
        "X-Parsed-By": [
            "org.apache.tika.parser.DefaultParser",
            "org.apache.tika.parser.csv.TextAndCSVParser"
        ],
        "X-TIKA:content_handler": "ToTextContentHandler",
        "X-TIKA:embedded_depth": "0",
        "X-TIKA:parse_time_millis": "1",
        "resourceName": "b'devreqst.c'"
    }
}