{
    "CHIKA1.SCR": {
        "modified": "1989-10-12 18:22:36",
        "size": "8.75KB",
        "md5": "f181aeaa50472c7ff19d5013be6db01e",
        "sha256": "8017eb7d6c510aa8da7edeba0d26b83af214b45e6c13f6d39a5bf92e3d9e01ce"
    },
    "Metadata": {
        "Content-Type": "application/octet-stream",
        "X-Parsed-By": "org.apache.tika.parser.EmptyParser",
        "X-TIKA:embedded_depth": "0",
        "X-TIKA:parse_time_millis": "0",
        "resourceName": "b'CHIKA1.SCR'"
    }
}