{
    "ending1_3.ssc": {
        "modified": "2020-10-06 13:38:51.519667",
        "size": "14.5KB",
        "md5": "fd78771e70562f2bc312ea3200702980",
        "sha256": "40d3e06fdaa740fce8a73e5d039a09d55e071fc7785080bd3a3d268c783280c8"
    },
    "Metadata": {
        "Content-Type": "application/octet-stream",
        "X-Parsed-By": "org.apache.tika.parser.EmptyParser",
        "X-TIKA:embedded_depth": "0",
        "X-TIKA:parse_time_millis": "0",
        "resourceName": "b'ending1_3.ssc'"
    }
}