{
    "map_mario_a_cover.txt": {
        "modified": "2020-10-06 13:38:21.504077",
        "size": "28.91KB",
        "md5": "872e4acd84a0fbacb8ad60c651fe2a66",
        "sha256": "ad17a21069ed7caa3cac1968c09b5a226abbea820d3f09d1253e321934681987"
    },
    "Metadata": {
        "Content-Encoding": "windows-1252",
        "Content-Type": "text/plain; charset=windows-1252",
        "X-Parsed-By": [
            "org.apache.tika.parser.DefaultParser",
            "org.apache.tika.parser.csv.TextAndCSVParser"
        ],
        "X-TIKA:content_handler": "ToTextContentHandler",
        "X-TIKA:embedded_depth": "0",
        "X-TIKA:parse_time_millis": "2",
        "resourceName": "b'map_mario_a_cover.txt'"
    }
}