{
    "Bailey.raw": {
        "modified": "2020-10-06 13:38:14.314880",
        "size": "3.5KB",
        "md5": "71937ff53cba463fd9d9f11eefd56764",
        "sha256": "15be8920ba18c5bb047e1aab20f12d440b6096ce2741d4e25d9b09d2c3f789c6"
    },
    "Metadata": {
        "Content-Type": "application/octet-stream",
        "X-Parsed-By": "org.apache.tika.parser.EmptyParser",
        "X-TIKA:embedded_depth": "0",
        "X-TIKA:parse_time_millis": "1",
        "resourceName": "b'Bailey.raw'"
    }
}