{
    "AboutInfo.java": {
        "modified": "2004-04-29 18:37:18",
        "size": "7.51KB",
        "md5": "c423cb2da955860856251b86dbd7d7a0",
        "sha256": "ec6d3fff2f7df04043b9199bb939609ae26d54e4d2d1c6c2ca9e3e3c6cef51a9"
    },
    "Metadata": {
        "Content-Encoding": "ISO-8859-1",
        "Content-Type": "text/plain; charset=ISO-8859-1",
        "X-Parsed-By": [
            "org.apache.tika.parser.DefaultParser",
            "org.apache.tika.parser.csv.TextAndCSVParser"
        ],
        "X-TIKA:content_handler": "ToTextContentHandler",
        "X-TIKA:embedded_depth": "0",
        "X-TIKA:parse_time_millis": "1",
        "resourceName": "b'AboutInfo.java'"
    }
}