{
    "AxisTestRedesign.html": {
        "modified": "2021-07-24 18:49:52.691408",
        "size": "9.27KB",
        "md5": "54ce2c2938137681dea2848925f601e5",
        "sha256": "8260ed188f8321581a71220e6428f1f17e241a7d2f37e470b06e01d1b6da2e86"
    },
    "Metadata": {
        "Content-Encoding": "ISO-8859-1",
        "Content-Type": "text/html; charset=ISO-8859-1",
        "X-Parsed-By": [
            "org.apache.tika.parser.DefaultParser",
            "org.apache.tika.parser.html.HtmlParser"
        ],
        "X-TIKA:content_handler": "ToTextContentHandler",
        "X-TIKA:embedded_depth": "0",
        "X-TIKA:parse_time_millis": "1",
        "dc:title": "Axis Test Rearchitecture",
        "resourceName": "b'AxisTestRedesign.html'",
        "title": "Axis Test Rearchitecture"
    }
}