{
    "ovl_weather_fine_rel.szs": {
        "modified": "2003-03-07 01:10:21",
        "size": "0.03KB",
        "md5": "cd4f09e3516c013d7376f7f4d2d879a9",
        "sha256": "8927454a10d146e603038979220fac1f6342d58d17296942c65c7beb7af06411"
    },
    "Metadata": {
        "Content-Type": "application/octet-stream",
        "X-Parsed-By": "org.apache.tika.parser.EmptyParser",
        "X-TIKA:embedded_depth": "0",
        "X-TIKA:parse_time_millis": "0",
        "resourceName": "b'ovl_weather_fine_rel.szs'"
    }
}