{
    "police_box_scene.szs": {
        "modified": "2003-03-07 01:10:31",
        "size": "0.14KB",
        "md5": "03525d6b457c23201a7ecc00534fdf68",
        "sha256": "bdea4590c22b368ff2332544c43bbaf085134dbe900c950e18507c796d53630b"
    },
    "Metadata": {
        "Content-Type": "application/octet-stream",
        "X-Parsed-By": "org.apache.tika.parser.EmptyParser",
        "X-TIKA:embedded_depth": "0",
        "X-TIKA:parse_time_millis": "0",
        "resourceName": "b'police_box_scene.szs'"
    }
}