{
    "nc_btn.acl": {
        "modified": "2005-08-25 18:40:28",
        "size": "0.5KB",
        "md5": "c72d37eb70f99bd552973c28dca5fb90",
        "sha256": "cb19d1f84e4b9045f0e823f959212428432b0dc0d1623b1a4af00e9ae6ddc703"
    },
    "Metadata": {
        "Content-Type": "application/octet-stream",
        "X-Parsed-By": "org.apache.tika.parser.EmptyParser",
        "X-TIKA:embedded_depth": "0",
        "X-TIKA:parse_time_millis": "1",
        "resourceName": "b'nc_btn.acl'"
    }
}