{
    "texture_pattern.h": {
        "modified": "2020-10-06 13:38:54.957460",
        "size": "2.93KB",
        "md5": "232d6c6984afc049e3ab27f9d32bb212",
        "sha256": "40f149c2bb198c6e873f7906f32f463058d8bc146fcfc8f8ce0380c0024d1a2d"
    },
    "Metadata": {
        "Content-Encoding": "windows-1252",
        "Content-Type": "text/plain; charset=windows-1252",
        "X-Parsed-By": [
            "org.apache.tika.parser.DefaultParser",
            "org.apache.tika.parser.csv.TextAndCSVParser"
        ],
        "X-TIKA:content_handler": "ToTextContentHandler",
        "X-TIKA:embedded_depth": "0",
        "X-TIKA:parse_time_millis": "0",
        "resourceName": "b'texture_pattern.h'"
    }
}