{
    "pwrite.c": {
        "modified": "2021-07-24 18:49:44.058237",
        "size": "1.97KB",
        "md5": "ac1be14e054d9bac71a0ffbef235fea2",
        "sha256": "98f0de605a66c5ac49f2d4b8a4ff827b1386fd0088cd15d56a5696155170ce21"
    },
    "Metadata": {
        "Content-Encoding": "ISO-8859-1",
        "Content-Type": "text/plain; charset=ISO-8859-1",
        "X-Parsed-By": [
            "org.apache.tika.parser.DefaultParser",
            "org.apache.tika.parser.csv.TextAndCSVParser"
        ],
        "X-TIKA:content_handler": "ToTextContentHandler",
        "X-TIKA:embedded_depth": "0",
        "X-TIKA:parse_time_millis": "1",
        "resourceName": "b'pwrite.c'"
    }
}