{
    "sleep.h": {
        "modified": "2020-10-06 13:37:04.488301",
        "size": "5.92KB",
        "md5": "62e7d75674ffbc5c67439ce1e36ab7a1",
        "sha256": "6828cbd7a34640f9e31e7dafbc3decb9dcd50eaa577048aacdf569041641fab2"
    },
    "Metadata": {
        "Content-Encoding": "Shift_JIS",
        "Content-Type": "text/plain; charset=Shift_JIS",
        "X-Parsed-By": [
            "org.apache.tika.parser.DefaultParser",
            "org.apache.tika.parser.csv.TextAndCSVParser"
        ],
        "X-TIKA:content_handler": "ToTextContentHandler",
        "X-TIKA:embedded_depth": "0",
        "X-TIKA:parse_time_millis": "1",
        "resourceName": "b'sleep.h'"
    }
}