{
    "import-c.yaml": {
        "modified": "2008-05-08 21:11:56",
        "size": "0.21KB",
        "md5": "1589d5fe57f2861e2d8756756e143820",
        "sha256": "470bd9e4deb9052b70e7bf55c1cde0a1f60f7046003c53d1cd886297615478de"
    },
    "Metadata": {
        "Content-Encoding": "ISO-8859-1",
        "Content-Type": "text/plain; charset=ISO-8859-1",
        "X-Parsed-By": [
            "org.apache.tika.parser.DefaultParser",
            "org.apache.tika.parser.csv.TextAndCSVParser"
        ],
        "X-TIKA:content_handler": "ToTextContentHandler",
        "X-TIKA:embedded_depth": "0",
        "X-TIKA:parse_time_millis": "1",
        "resourceName": "b'import-c.yaml'"
    }
}