{
    "DefaultSimilarity.java": {
        "modified": "2003-01-29 08:18:54",
        "size": "3.68KB",
        "md5": "68c07017ab14dfd22753bfe8c4c59040",
        "sha256": "7b08f82904810753ed2b20fd6e1d18598e4e6728d4483a4d5d7928f060e66e95"
    },
    "Metadata": {
        "Content-Encoding": "ISO-8859-1",
        "Content-Type": "text/plain; charset=ISO-8859-1",
        "X-Parsed-By": [
            "org.apache.tika.parser.DefaultParser",
            "org.apache.tika.parser.csv.TextAndCSVParser"
        ],
        "X-TIKA:content_handler": "ToTextContentHandler",
        "X-TIKA:embedded_depth": "0",
        "X-TIKA:parse_time_millis": "0",
        "resourceName": "b'DefaultSimilarity.java'"
    }
}