{
    "jmemname.c": {
        "modified": "1997-09-14 14:35:10",
        "size": "8.12KB",
        "md5": "719f6097de742d244c6680941795fa3e",
        "sha256": "c6318c7b484c26354ac3e6164c15403b6445d5eb0d81699b7e5c4106bf4e3e9e"
    },
    "Metadata": {
        "Content-Encoding": "ISO-8859-1",
        "Content-Type": "text/plain; charset=ISO-8859-1",
        "X-Parsed-By": [
            "org.apache.tika.parser.DefaultParser",
            "org.apache.tika.parser.csv.TextAndCSVParser"
        ],
        "X-TIKA:content_handler": "ToTextContentHandler",
        "X-TIKA:embedded_depth": "0",
        "X-TIKA:parse_time_millis": "1",
        "resourceName": "b'jmemname.c'"
    }
}