{
    "start.S": {
        "modified": "2021-07-24 18:49:44.438229",
        "size": "0.88KB",
        "md5": "c9b44b96d514ff6d2e967ff51771cf5a",
        "sha256": "e1c5a5cc8a1669187d1ca4988d4602a3a72048b51d3a22e1057d0cda32f70d69"
    },
    "Metadata": {
        "Content-Encoding": "ISO-8859-1",
        "Content-Type": "text/plain; charset=ISO-8859-1",
        "X-Parsed-By": [
            "org.apache.tika.parser.DefaultParser",
            "org.apache.tika.parser.csv.TextAndCSVParser"
        ],
        "X-TIKA:content_handler": "ToTextContentHandler",
        "X-TIKA:embedded_depth": "0",
        "X-TIKA:parse_time_millis": "0",
        "resourceName": "b'start.S'"
    }
}