{
    "930718-1.c": {
        "modified": "2021-07-24 18:49:42.444934",
        "size": "0.36KB",
        "md5": "de35b106caa372b8a241433073479bec",
        "sha256": "e7aad6d16af8c114107bc9c70a2f767bd0e84d27001c57a2183de3d09fcef3a0"
    },
    "Metadata": {
        "Content-Encoding": "ISO-8859-1",
        "Content-Type": "text/plain; charset=ISO-8859-1",
        "X-Parsed-By": [
            "org.apache.tika.parser.DefaultParser",
            "org.apache.tika.parser.csv.TextAndCSVParser"
        ],
        "X-TIKA:content_handler": "ToTextContentHandler",
        "X-TIKA:embedded_depth": "0",
        "X-TIKA:parse_time_millis": "1",
        "resourceName": "b'930718-1.c'"
    }
}