{
    "a52.h": {
        "modified": "2021-07-24 18:49:49.288138",
        "size": "4.3KB",
        "md5": "784db5614648e90de7116e265f4b67a0",
        "sha256": "04f0eb903c3cf924def75b1288474ccc1544b4f82265246cb6f3029254ec7824"
    },
    "Metadata": {
        "Content-Encoding": "ISO-8859-1",
        "Content-Type": "text/plain; charset=ISO-8859-1",
        "X-Parsed-By": [
            "org.apache.tika.parser.DefaultParser",
            "org.apache.tika.parser.csv.TextAndCSVParser"
        ],
        "X-TIKA:content_handler": "ToTextContentHandler",
        "X-TIKA:embedded_depth": "0",
        "X-TIKA:parse_time_millis": "1",
        "resourceName": "b'a52.h'"
    }
}