{
    "s-long-double.c": {
        "modified": "2021-07-24 18:49:43.041589",
        "size": "0.46KB",
        "md5": "30412ec47c92ed38d7e9e594453a5c2d",
        "sha256": "06d66542c95b552dd5698bd1c5d3f369730c1f0ebd1e893b7de3dca54a860da1"
    },
    "Metadata": {
        "Content-Encoding": "ISO-8859-1",
        "Content-Type": "text/x-csrc; charset=ISO-8859-1",
        "X-Parsed-By": [
            "org.apache.tika.parser.DefaultParser",
            "org.apache.tika.parser.csv.TextAndCSVParser"
        ],
        "X-TIKA:content_handler": "ToTextContentHandler",
        "X-TIKA:embedded_depth": "0",
        "X-TIKA:parse_time_millis": "1",
        "resourceName": "b's-long-double.c'"
    }
}