{
    "MMTBL.ASM": {
        "modified": "1995-07-06 16:29:46",
        "size": "106.95KB",
        "md5": "e2f7ed8d91304ba09a4e45fa1578a284",
        "sha256": "3f3cf1189665a9b701eb56185a5c72e44d91f807082c7c905c8499f25332a198"
    },
    "Metadata": {
        "Content-Encoding": "windows-1252",
        "Content-Type": "text/plain; charset=windows-1252",
        "X-Parsed-By": [
            "org.apache.tika.parser.DefaultParser",
            "org.apache.tika.parser.csv.TextAndCSVParser"
        ],
        "X-TIKA:content_handler": "ToTextContentHandler",
        "X-TIKA:embedded_depth": "0",
        "X-TIKA:parse_time_millis": "2",
        "resourceName": "b'MMTBL.ASM'"
    }
}