{
    "ohci1.elf": {
        "modified": "2011-10-18 11:58:25",
        "size": "65.81KB",
        "md5": "1adf31e36807a762b5725a7065a1cc84",
        "sha256": "30f181c4bc17f19f3e335de5a0562462e9608f3cf08a636bdabe52b38b3b293a"
    },
    "Metadata": {
        "Content-Type": "application/x-executable",
        "X-Parsed-By": [
            "org.apache.tika.parser.DefaultParser",
            "org.apache.tika.parser.executable.ExecutableParser"
        ],
        "X-TIKA:embedded_depth": "0",
        "X-TIKA:parse_time_millis": "1",
        "machine:architectureBits": "32",
        "machine:endian": "Big",
        "machine:machineType": "ARM",
        "machine:platform": "ARM",
        "resourceName": "b'ohci1.elf'"
    }
}