{
    "HerreraX.GSM": {
        "modified": "2020-10-06 13:38:12.034552",
        "size": "2.07KB",
        "md5": "73e2ec58560090e63b22a3eeb954bc30",
        "sha256": "dd307df21af103d6f8dff0edc55d1d558dba8cd3160a6d936de09d0fefc7251d"
    },
    "Metadata": {
        "Content-Type": "application/octet-stream",
        "X-Parsed-By": "org.apache.tika.parser.EmptyParser",
        "X-TIKA:embedded_depth": "0",
        "X-TIKA:parse_time_millis": "1",
        "resourceName": "b'HerreraX.GSM'"
    }
}