{
    "printstashedacl.py": {
        "modified": "2005-09-29 05:56:25",
        "size": "0.22KB",
        "md5": "e0c16d27f14d20f0c4811eb12b4b7920",
        "sha256": "e8156113c575035d261084716a3e511443b3345246057832c6f2e50e6002dfe8"
    },
    "Metadata": {
        "Content-Encoding": "ISO-8859-1",
        "Content-Type": "text/plain; charset=ISO-8859-1",
        "X-Parsed-By": [
            "org.apache.tika.parser.DefaultParser",
            "org.apache.tika.parser.csv.TextAndCSVParser"
        ],
        "X-TIKA:content_handler": "ToTextContentHandler",
        "X-TIKA:embedded_depth": "0",
        "X-TIKA:parse_time_millis": "0",
        "resourceName": "b'printstashedacl.py'"
    }
}