{
    "map.h": {
        "modified": "1994-07-27 19:59:24",
        "size": "2.61KB",
        "md5": "c7786ad77c5ae01f320a3d1ce20a3f5f",
        "sha256": "e991b100ed80e9d9cdb6c20b5c60ec2c67470b7e75ecc4a9070849d8b7d74148"
    },
    "Metadata": {
        "Content-Encoding": "ISO-8859-1",
        "Content-Type": "text/plain; charset=ISO-8859-1",
        "X-Parsed-By": [
            "org.apache.tika.parser.DefaultParser",
            "org.apache.tika.parser.csv.TextAndCSVParser"
        ],
        "X-TIKA:content_handler": "ToTextContentHandler",
        "X-TIKA:embedded_depth": "0",
        "X-TIKA:parse_time_millis": "1",
        "resourceName": "b'map.h'"
    }
}