{
    "threaddemo2D.elf": {
        "modified": "2006-03-22 17:59:56",
        "size": "282.95KB",
        "md5": "56596888cf5e140ea612bfe12272d82e",
        "sha256": "c208f8d3fad5f38303e705831d644e43eb6698ba0af86d8db74d8db03019b229"
    },
    "Metadata": {
        "Content-Type": "application/x-executable",
        "X-Parsed-By": [
            "org.apache.tika.parser.DefaultParser",
            "org.apache.tika.parser.executable.ExecutableParser"
        ],
        "X-TIKA:embedded_depth": "0",
        "X-TIKA:parse_time_millis": "1",
        "machine:architectureBits": "32",
        "machine:endian": "Big",
        "machine:machineType": "PPC",
        "resourceName": "b'threaddemo2D.elf'"
    }
}