{
    "BaseOptionTemplateSection.html": {
        "modified": "2005-06-27 15:12:12",
        "size": "14.42KB",
        "md5": "c9e8e2577b919be66a84361ce89c86ce",
        "sha256": "fcadebe468b3e27cbe1f494f7846b810cc35a11146f040d04b051e03d7ec3b27"
    },
    "Metadata": {
        "Content-Encoding": "ISO-8859-1",
        "Content-Type": "text/html; charset=ISO-8859-1",
        "Content-Type-Hint": "text/html; charset=iso-8859-1",
        "X-Parsed-By": [
            "org.apache.tika.parser.DefaultParser",
            "org.apache.tika.parser.html.HtmlParser"
        ],
        "X-TIKA:content_handler": "ToTextContentHandler",
        "X-TIKA:embedded_depth": "0",
        "X-TIKA:parse_time_millis": "1",
        "dc:title": "Uses of Class org.eclipse.pde.ui.templates.BaseOptionTemplateSection (Eclipse PDE API Specification)",
        "resourceName": "b'BaseOptionTemplateSection.html'",
        "title": "Uses of Class org.eclipse.pde.ui.templates.BaseOptionTemplateSection (Eclipse PDE API Specification)"
    }
}