{
    "ssl_socket.C": {
        "modified": "2021-07-24 18:49:49.171474",
        "size": "1.21KB",
        "md5": "6fbbad16717b1ce64890dfbda35cf426",
        "sha256": "1b78b2e54be5b9e937f741c8ddff58e4384030292cb914391cfe1025ea93139c"
    },
    "Metadata": {
        "Content-Encoding": "ISO-8859-1",
        "Content-Type": "text/x-csrc; charset=ISO-8859-1",
        "X-Parsed-By": [
            "org.apache.tika.parser.DefaultParser",
            "org.apache.tika.parser.csv.TextAndCSVParser"
        ],
        "X-TIKA:content_handler": "ToTextContentHandler",
        "X-TIKA:embedded_depth": "0",
        "X-TIKA:parse_time_millis": "1",
        "resourceName": "b'ssl_socket.C'"
    }
}