{
    "DP_Berries.xls": {
        "modified": "2020-10-06 13:37:24.871448",
        "size": "81.5KB",
        "md5": "ca47da38d4db7237fa12572f88af7f0a",
        "sha256": "17d12a4074075209df3d16e40ea9a5e05572a6b176478a7312c5b64a993c35ff"
    },
    "Metadata": {
        "Application-Name": "Microsoft Excel",
        "Author": "nakao_noriko",
        "Company": "任天堂株式会社開発一部",
        "Content-Type": "application/vnd.ms-excel",
        "Creation-Date": "2006-08-28T05:20:01Z",
        "Last-Author": "DEDEIMAR",
        "Last-Modified": "2007-03-22T13:41:27Z",
        "Last-Save-Date": "2007-03-22T13:41:27Z",
        "X-Parsed-By": [
            "org.apache.tika.parser.DefaultParser",
            "org.apache.tika.parser.microsoft.OfficeParser"
        ],
        "X-TIKA:content_handler": "ToTextContentHandler",
        "X-TIKA:embedded_depth": "0",
        "X-TIKA:parse_time_millis": "6",
        "creator": "nakao_noriko",
        "date": "2007-03-22T13:41:27Z",
        "dc:creator": "nakao_noriko",
        "dcterms:created": "2006-08-28T05:20:01Z",
        "dcterms:modified": "2007-03-22T13:41:27Z",
        "extended-properties:Application": "Microsoft Excel",
        "extended-properties:Company": "任天堂株式会社開発一部",
        "meta:author": "nakao_noriko",
        "meta:creation-date": "2006-08-28T05:20:01Z",
        "meta:last-author": "DEDEIMAR",
        "meta:save-date": "2007-03-22T13:41:27Z",
        "modified": "2007-03-22T13:41:27Z",
        "resourceName": "b'DP_Berries.xls'"
    }
}