{
    "mario_titleMatrix.c": {
        "modified": "2020-10-06 13:39:14.789049",
        "size": "0.56KB",
        "md5": "e38d16fe0fcec3990abbfe227ddfeb1f",
        "sha256": "477aac8d6b57057cddba63a131ce094c94cccf83abf39991706a7d941481dc44"
    },
    "Metadata": {
        "Content-Encoding": "ISO-8859-1",
        "Content-Type": "text/plain; charset=ISO-8859-1",
        "X-Parsed-By": [
            "org.apache.tika.parser.DefaultParser",
            "org.apache.tika.parser.csv.TextAndCSVParser"
        ],
        "X-TIKA:content_handler": "ToTextContentHandler",
        "X-TIKA:embedded_depth": "0",
        "X-TIKA:parse_time_millis": "1",
        "resourceName": "b'mario_titleMatrix.c'"
    }
}