{
    "s_atanl.S": {
        "modified": "2021-07-24 18:49:43.994905",
        "size": "0.27KB",
        "md5": "cb4c7c0abba8d0f72cfdbc3fd809e7b3",
        "sha256": "eec350ffb198e564ab9ecc9eaa9393bccf853e15eb83a52d4afad743de4d9aa2"
    },
    "Metadata": {
        "Content-Encoding": "ISO-8859-1",
        "Content-Type": "text/plain; charset=ISO-8859-1",
        "X-Parsed-By": [
            "org.apache.tika.parser.DefaultParser",
            "org.apache.tika.parser.csv.TextAndCSVParser"
        ],
        "X-TIKA:content_handler": "ToTextContentHandler",
        "X-TIKA:embedded_depth": "0",
        "X-TIKA:parse_time_millis": "1",
        "resourceName": "b's_atanl.S'"
    }
}