{
    "yoko_silen_TX.rgb": {
        "modified": "2020-10-06 13:38:23.579713",
        "size": "5.01KB",
        "md5": "62ca5846259bda4b78598a2a05415818",
        "sha256": "301615b5d6bfd0c076098c0c0b1fe9752cf783f8ffde31fbceef13d365a4fd03"
    },
    "Metadata": {
        "Content-Type": "image/x-rgb",
        "X-Parsed-By": "org.apache.tika.parser.EmptyParser",
        "X-TIKA:embedded_depth": "0",
        "X-TIKA:parse_time_millis": "0",
        "resourceName": "b'yoko_silen_TX.rgb'"
    }
}