{
    "streamable.c": {
        "modified": "2021-07-24 18:49:47.448173",
        "size": "7.22KB",
        "md5": "83932cec87296f2ff60f361f6ad36ffc",
        "sha256": "493ff31e54fadfb70730e5f299d325e52fbc39516c5542a0911f61c8e61e9c53"
    },
    "Metadata": {
        "Content-Encoding": "ISO-8859-1",
        "Content-Type": "text/plain; charset=ISO-8859-1",
        "X-Parsed-By": [
            "org.apache.tika.parser.DefaultParser",
            "org.apache.tika.parser.csv.TextAndCSVParser"
        ],
        "X-TIKA:content_handler": "ToTextContentHandler",
        "X-TIKA:embedded_depth": "0",
        "X-TIKA:parse_time_millis": "1",
        "resourceName": "b'streamable.c'"
    }
}