{
    "room_cat_3_2.c": {
        "modified": "2020-10-06 13:38:31.777853",
        "size": "2.06KB",
        "md5": "492c4a1328b1a0c72b6f56d660948906",
        "sha256": "9f37cbf7aaf9dc1b2ce3b115b665f7316ca9d807d77e8226a76fe05aac64850e"
    },
    "Metadata": {
        "Content-Encoding": "ISO-8859-1",
        "Content-Type": "text/tsv; charset=ISO-8859-1; delimiter=tab",
        "X-Parsed-By": [
            "org.apache.tika.parser.DefaultParser",
            "org.apache.tika.parser.csv.TextAndCSVParser"
        ],
        "X-TIKA:content_handler": "ToTextContentHandler",
        "X-TIKA:embedded_depth": "0",
        "X-TIKA:parse_time_millis": "0",
        "csv:delimiter": "tab",
        "resourceName": "b'room_cat_3_2.c'"
    }
}