{
    "e_kusaeff2.imd": {
        "modified": "2020-10-06 13:37:05.753917",
        "size": "5.9KB",
        "md5": "ca121127c42c2dccebc4d232f663e382",
        "sha256": "b0e57e276487cfa40a377179a09de7d52313fd326addedf385cd3813c477262a"
    },
    "Metadata": {
        "Content-Type": "application/xml",
        "X-Parsed-By": [
            "org.apache.tika.parser.DefaultParser",
            "org.apache.tika.parser.xml.DcXMLParser"
        ],
        "X-TIKA:content_handler": "ToTextContentHandler",
        "X-TIKA:embedded_depth": "0",
        "X-TIKA:parse_time_millis": "0",
        "resourceName": "b'e_kusaeff2.imd'"
    }
}