{
    "feholdexcpt.c": {
        "modified": "2021-07-24 18:49:44.028237",
        "size": "1.26KB",
        "md5": "b1dcdfa19535b56fd1047213067a4024",
        "sha256": "81bce3dba1b61c9f4806c451e99cb831448d6f6ecba773b5a14c23273f69a01c"
    },
    "Metadata": {
        "Content-Encoding": "ISO-8859-1",
        "Content-Type": "text/plain; charset=ISO-8859-1",
        "X-Parsed-By": [
            "org.apache.tika.parser.DefaultParser",
            "org.apache.tika.parser.csv.TextAndCSVParser"
        ],
        "X-TIKA:content_handler": "ToTextContentHandler",
        "X-TIKA:embedded_depth": "0",
        "X-TIKA:parse_time_millis": "1",
        "resourceName": "b'feholdexcpt.c'"
    }
}