{
    "CancelableProblemFactory.java": {
        "modified": "2005-02-22 20:47:30",
        "size": "1.53KB",
        "md5": "c4e47673bd00b3d00792ad5da4e2e6ad",
        "sha256": "141fd9dea807f197cec25fbd27eed5189fb6d7e0e39c2cc11611d532c277c259"
    },
    "Metadata": {
        "Content-Encoding": "ISO-8859-1",
        "Content-Type": "text/plain; charset=ISO-8859-1",
        "X-Parsed-By": [
            "org.apache.tika.parser.DefaultParser",
            "org.apache.tika.parser.csv.TextAndCSVParser"
        ],
        "X-TIKA:content_handler": "ToTextContentHandler",
        "X-TIKA:embedded_depth": "0",
        "X-TIKA:parse_time_millis": "1",
        "resourceName": "b'CancelableProblemFactory.java'"
    }
}