{
    "mi-console.c": {
        "modified": "2021-07-24 18:49:45.374878",
        "size": "0.21KB",
        "md5": "2748c57b9ccc6f5d68d793f547c07d42",
        "sha256": "e2bc7698a21199ef4f458823c157ba339067ee24fe1dd60383ebeeb3665ca2d1"
    },
    "Metadata": {
        "Content-Encoding": "ISO-8859-1",
        "Content-Type": "text/plain; charset=ISO-8859-1",
        "X-Parsed-By": [
            "org.apache.tika.parser.DefaultParser",
            "org.apache.tika.parser.csv.TextAndCSVParser"
        ],
        "X-TIKA:content_handler": "ToTextContentHandler",
        "X-TIKA:embedded_depth": "0",
        "X-TIKA:parse_time_millis": "1",
        "resourceName": "b'mi-console.c'"
    }
}