{
    "GXTexObjInitFlow.html": {
        "modified": "2006-03-04 18:23:08",
        "size": "2.94KB",
        "md5": "7de1b6684bd4eafdf89904bd86369165",
        "sha256": "6e59c786adb0bc4948adc2e91b073fc34a969f8cacff3bb85fc30955afe424a4"
    },
    "Metadata": {
        "Content-Encoding": "windows-1252",
        "Content-Style-Type": "text/css",
        "Content-Type": "text/html; charset=windows-1252",
        "Content-Type-Hint": "text/html; charset=windows-1252",
        "GENERATOR": "Microsoft FrontPage 5.0",
        "X-Parsed-By": [
            "org.apache.tika.parser.DefaultParser",
            "org.apache.tika.parser.html.HtmlParser"
        ],
        "X-TIKA:content_handler": "ToTextContentHandler",
        "X-TIKA:embedded_depth": "0",
        "X-TIKA:parse_time_millis": "1",
        "dc:title": "GXTexObj Initialization Flow",
        "resourceName": "b'GXTexObjInitFlow.html'",
        "title": "GXTexObj Initialization Flow"
    }
}