{
    "cyberblade_vid.c": {
        "modified": "2021-07-24 18:49:49.368137",
        "size": "15.73KB",
        "md5": "6ef6bcdc217f97a660e5164a0e63c014",
        "sha256": "cb7c5a91ac0ab513097fd9e00834269020db793b618a7424c40420fb97e65629"
    },
    "Metadata": {
        "Content-Encoding": "ISO-8859-1",
        "Content-Type": "text/plain; charset=ISO-8859-1",
        "X-Parsed-By": [
            "org.apache.tika.parser.DefaultParser",
            "org.apache.tika.parser.csv.TextAndCSVParser"
        ],
        "X-TIKA:content_handler": "ToTextContentHandler",
        "X-TIKA:embedded_depth": "0",
        "X-TIKA:parse_time_millis": "2",
        "resourceName": "b'cyberblade_vid.c'"
    }
}