{
    "vs_no_entry.o": {
        "modified": "2020-10-06 13:40:50.038466",
        "size": "0.82KB",
        "md5": "6e2e02d9cb8b3735f1c9e906f402924d",
        "sha256": "5edf6af77de77a18714a19109c23c719d0a55604c78b4b2145975da81380f3ff"
    },
    "Metadata": {
        "Content-Type": "application/x-object",
        "X-Parsed-By": [
            "org.apache.tika.parser.DefaultParser",
            "org.apache.tika.parser.executable.ExecutableParser"
        ],
        "X-TIKA:embedded_depth": "0",
        "X-TIKA:parse_time_millis": "1",
        "machine:architectureBits": "32",
        "machine:endian": "Little",
        "resourceName": "b'vs_no_entry.o'"
    }
}