{
    "cdesc-FormatDecodeError.yaml": {
        "modified": "2008-05-08 21:11:56",
        "size": "0.22KB",
        "md5": "1a6dd475ec174623cdc1b19ef4601094",
        "sha256": "2cbf32135adfca67bf0c03b9d99747fa0d8d56f2012b768b3b2cf292915d24a0"
    },
    "Metadata": {
        "Content-Encoding": "ISO-8859-1",
        "Content-Type": "text/plain; charset=ISO-8859-1",
        "X-Parsed-By": [
            "org.apache.tika.parser.DefaultParser",
            "org.apache.tika.parser.csv.TextAndCSVParser"
        ],
        "X-TIKA:content_handler": "ToTextContentHandler",
        "X-TIKA:embedded_depth": "0",
        "X-TIKA:parse_time_millis": "0",
        "resourceName": "b'cdesc-FormatDecodeError.yaml'"
    }
}