{
    "makeAppending_More_Text_to_Variables.html": {
        "modified": "2020-10-06 13:40:37.093146",
        "size": "11.35KB",
        "md5": "06a972d7c2e0704116c3568e6159bf23",
        "sha256": "ad3c8cac53bd87636cec584e6b43a76d4d38c98df4030eb578d10b6c3d9c6fe8"
    },
    "Metadata": {
        "Content-Encoding": "windows-1252",
        "Content-Type": "text/html; charset=windows-1252",
        "X-Parsed-By": [
            "org.apache.tika.parser.DefaultParser",
            "org.apache.tika.parser.html.HtmlParser"
        ],
        "X-TIKA:content_handler": "ToTextContentHandler",
        "X-TIKA:embedded_depth": "0",
        "X-TIKA:parse_time_millis": "2",
        "dc:title": "Appending More Text to Variables",
        "resourceName": "b'makeAppending_More_Text_to_Variables.html'",
        "title": "Appending More Text to Variables"
    }
}