{
    "t32.C": {
        "modified": "2021-07-24 18:49:41.811612",
        "size": "0.31KB",
        "md5": "27277911ede448fd10f27c9f07a130ea",
        "sha256": "9417a3ed94d6c0683f3f5a341f76c5e9dc821c5aba165c883f4f748009a37229"
    },
    "Metadata": {
        "Content-Encoding": "ISO-8859-1",
        "Content-Type": "text/plain; charset=ISO-8859-1",
        "X-Parsed-By": [
            "org.apache.tika.parser.DefaultParser",
            "org.apache.tika.parser.csv.TextAndCSVParser"
        ],
        "X-TIKA:content_handler": "ToTextContentHandler",
        "X-TIKA:embedded_depth": "0",
        "X-TIKA:parse_time_millis": "0",
        "resourceName": "b't32.C'"
    }
}