{
    "BB_HW_RELEASES_TO_XS.sql": {
        "modified": "2021-07-24 18:49:56.431338",
        "size": "0.09KB",
        "md5": "121288ab1d41ca165b9bd49fa85ade4e",
        "sha256": "596fdcf6b7747c4c4e7ee38ce6b619d5e5ec955a0b6ced1556738b5e7a20604c"
    },
    "Metadata": {
        "Content-Encoding": "ISO-8859-1",
        "Content-Type": "text/plain; charset=ISO-8859-1",
        "X-Parsed-By": [
            "org.apache.tika.parser.DefaultParser",
            "org.apache.tika.parser.csv.TextAndCSVParser"
        ],
        "X-TIKA:content_handler": "ToTextContentHandler",
        "X-TIKA:embedded_depth": "0",
        "X-TIKA:parse_time_millis": "1",
        "resourceName": "b'BB_HW_RELEASES_TO_XS.sql'"
    }
}