{
    "be_069.s": {
        "modified": "2020-10-06 13:37:04.818301",
        "size": "0.48KB",
        "md5": "4bd043060310c15184c0c91529ed9065",
        "sha256": "601fc0f06b624b7142155082977e7fe30050d716aa8a098de8a42bb9a4ca1bf0"
    },
    "Metadata": {
        "Content-Encoding": "Shift_JIS",
        "Content-Type": "text/plain; charset=Shift_JIS",
        "X-Parsed-By": [
            "org.apache.tika.parser.DefaultParser",
            "org.apache.tika.parser.csv.TextAndCSVParser"
        ],
        "X-TIKA:content_handler": "ToTextContentHandler",
        "X-TIKA:embedded_depth": "0",
        "X-TIKA:parse_time_millis": "1",
        "resourceName": "b'be_069.s'"
    }
}