{
    "geteuid.S": {
        "modified": "2021-07-24 18:49:44.044904",
        "size": "1.05KB",
        "md5": "4ae59dc7e03d9f2336dff7847dac45f0",
        "sha256": "74791e852a84b798566093d9a44d97475125b3304d0661a895ea50ad5b45a7f8"
    },
    "Metadata": {
        "Content-Encoding": "ISO-8859-1",
        "Content-Type": "text/plain; charset=ISO-8859-1",
        "X-Parsed-By": [
            "org.apache.tika.parser.DefaultParser",
            "org.apache.tika.parser.csv.TextAndCSVParser"
        ],
        "X-TIKA:content_handler": "ToTextContentHandler",
        "X-TIKA:embedded_depth": "0",
        "X-TIKA:parse_time_millis": "0",
        "resourceName": "b'geteuid.S'"
    }
}