{
    "cloth047_tex.out": {
        "modified": "2020-10-06 13:38:27.004864",
        "size": "7.02KB",
        "md5": "379444572acb66c1c4307c15bffd159d",
        "sha256": "f4644a69da05953d9df7f9b5e6b01cc83449926c6a2d6eecb13a3e71391b0e2a"
    },
    "Metadata": {
        "Content-Encoding": "ISO-8859-1",
        "Content-Type": "text/plain; charset=ISO-8859-1",
        "X-Parsed-By": [
            "org.apache.tika.parser.DefaultParser",
            "org.apache.tika.parser.csv.TextAndCSVParser"
        ],
        "X-TIKA:content_handler": "ToTextContentHandler",
        "X-TIKA:embedded_depth": "0",
        "X-TIKA:parse_time_millis": "1",
        "resourceName": "b'cloth047_tex.out'"
    }
}