{
    "arc.h": {
        "modified": "2020-10-06 13:42:13.364246",
        "size": "11.74KB",
        "md5": "8f9369e708a03c9add000c7680092b48",
        "sha256": "17ac81f97a9078677e9c55acc852e306b1ba73b2b10e0dfc2a5c893daa8cbc40"
    },
    "Metadata": {
        "Content-Encoding": "ISO-8859-1",
        "Content-Type": "text/plain; charset=ISO-8859-1",
        "X-Parsed-By": [
            "org.apache.tika.parser.DefaultParser",
            "org.apache.tika.parser.csv.TextAndCSVParser"
        ],
        "X-TIKA:content_handler": "ToTextContentHandler",
        "X-TIKA:embedded_depth": "0",
        "X-TIKA:parse_time_millis": "1",
        "resourceName": "b'arc.h'"
    }
}