{
    "AC_sakana_02_sebire.o": {
        "modified": "2020-10-06 13:39:11.493855",
        "size": "3.34KB",
        "md5": "0745ad6646de581a878e408f630ab873",
        "sha256": "c21beb0eb436def47ec472bdd43f9e081dd2f9584a2a836c84643c9fa910f095"
    },
    "Metadata": {
        "Content-Type": "application/x-object",
        "X-Parsed-By": [
            "org.apache.tika.parser.DefaultParser",
            "org.apache.tika.parser.executable.ExecutableParser"
        ],
        "X-TIKA:embedded_depth": "0",
        "X-TIKA:parse_time_millis": "0",
        "machine:architectureBits": "32",
        "machine:endian": "Big",
        "machine:machineType": "MIPS",
        "resourceName": "b'AC_sakana_02_sebire.o'"
    }
}