{
    "zone_c04r0202.evc": {
        "modified": "2020-10-06 13:37:13.317806",
        "size": "0.6KB",
        "md5": "84379bd512370b88c933de9e48a3f7b5",
        "sha256": "e7bd6e81118542614e52fe4348ca91f3b999f7083ac62891f600e62ebf7c9787"
    },
    "Metadata": {
        "Content-Encoding": "ISO-8859-1",
        "Content-Type": "text/plain; charset=ISO-8859-1",
        "X-Parsed-By": [
            "org.apache.tika.parser.DefaultParser",
            "org.apache.tika.parser.csv.TextAndCSVParser"
        ],
        "X-TIKA:content_handler": "ToTextContentHandler",
        "X-TIKA:embedded_depth": "0",
        "X-TIKA:parse_time_millis": "1",
        "resourceName": "b'zone_c04r0202.evc'"
    }
}