{
    "curl_formadd.3": {
        "modified": "2021-07-24 18:49:46.211529",
        "size": "6.74KB",
        "md5": "34f823eb7abe35a09964b9dba1c16c8b",
        "sha256": "6c2da1ec7fc0d744ae025684a2334a1b83e81567f87cbe3e787ce29ed653b3ab"
    },
    "Metadata": {
        "Content-Encoding": "ISO-8859-1",
        "Content-Type": "text/troff; charset=ISO-8859-1",
        "X-Parsed-By": [
            "org.apache.tika.parser.DefaultParser",
            "org.apache.tika.parser.csv.TextAndCSVParser"
        ],
        "X-TIKA:content_handler": "ToTextContentHandler",
        "X-TIKA:embedded_depth": "0",
        "X-TIKA:parse_time_millis": "1",
        "resourceName": "b'curl_formadd.3'"
    }
}