{
    "AttachmentsImpl.html": {
        "modified": "2005-10-05 19:46:54",
        "size": "47.53KB",
        "md5": "96bfd79c90d520c9ab9e33aa0691475a",
        "sha256": "a6f2f5b8fe8e051aef1c43aa6d90f03e828947501248703168aedebaa4e69d55"
    },
    "Metadata": {
        "Content-Encoding": "windows-1252",
        "Content-Type": "text/html; charset=windows-1252",
        "X-Parsed-By": [
            "org.apache.tika.parser.DefaultParser",
            "org.apache.tika.parser.html.HtmlParser"
        ],
        "X-TIKA:content_handler": "ToTextContentHandler",
        "X-TIKA:embedded_depth": "0",
        "X-TIKA:parse_time_millis": "6",
        "dc:title": "AttachmentsImpl (Axis API)",
        "keywords": "org.apache.axis.attachments.AttachmentsImpl class",
        "resourceName": "b'AttachmentsImpl.html'",
        "title": "AttachmentsImpl (Axis API)"
    }
}