{
    "ds_netcard_20060809_1.doc": {
        "modified": "2020-10-06 13:40:37.431146",
        "size": "27.5KB",
        "md5": "83c6c1cca3371975cf851b463bfe3f0b",
        "sha256": "30bd3ad585baae7eb6b67488f405d5c2aec42f6af1bb64cea4efd4a7495bd1b7"
    },
    "Metadata": {
        "Application-Name": "Microsoft Word 9.0",
        "Author": " Andy Chan",
        "Character Count": "1671",
        "Comments": "",
        "Company": "BroadOn Communications ",
        "Content-Type": "application/msword",
        "Creation-Date": "2006-08-10T06:13:00Z",
        "Edit-Time": "16800000000",
        "Keywords": "",
        "Last-Author": "Paul Mielke",
        "Last-Modified": "2006-08-10T06:42:00Z",
        "Last-Printed": "2005-12-08T02:06:00Z",
        "Last-Save-Date": "2006-08-10T06:42:00Z",
        "Page-Count": "1",
        "Revision-Number": "3",
        "Template": "Normal.dot",
        "Word-Count": "293",
        "X-Parsed-By": [
            "org.apache.tika.parser.DefaultParser",
            "org.apache.tika.parser.microsoft.OfficeParser"
        ],
        "X-TIKA:content_handler": "ToTextContentHandler",
        "X-TIKA:embedded_depth": "0",
        "X-TIKA:origResourceName": [
            "C:\\Documents and Settings\\paulm\\Desktop\\SC\\DS_NC\\ds_netcard_20060727.doc",
            "C:\\Documents and Settings\\paulm\\Application Data\\Microsoft\\Word\\AutoRecovery save of ds_netcard_20060727.asd",
            "E:\\SC\\DS_NC\\ds_netcard_20060727.doc",
            "E:\\SC\\DS_NC\\ds_netcard_20060803_2.doc",
            "C:\\Documents and Settings\\paulm\\Application Data\\Microsoft\\Word\\AutoRecovery save of ds_netcard_20060803_2.asd",
            "E:\\SC\\DS_NC\\ds_netcard_20060803_2.doc",
            "E:\\SC\\DS_NC\\ds_netcard_20060809_1.doc",
            "C:\\Documents and Settings\\paulm\\Application Data\\Microsoft\\Word\\AutoRecovery save of ds_netcard_20060809_1.asd",
            "C:\\Documents and Settings\\paulm\\Application Data\\Microsoft\\Word\\AutoRecovery save of ds_netcard_20060809_1.asd",
            "E:\\SC\\DS_NC\\ds_netcard_20060809_1.doc"
        ],
        "X-TIKA:parse_time_millis": "4",
        "comment": "",
        "cp:revision": "3",
        "cp:subject": "",
        "creator": " Andy Chan",
        "date": "2006-08-10T06:42:00Z",
        "dc:creator": " Andy Chan",
        "dc:subject": "",
        "dc:title": "System Boot on NC",
        "dcterms:created": "2006-08-10T06:13:00Z",
        "dcterms:modified": "2006-08-10T06:42:00Z",
        "extended-properties:Application": "Microsoft Word 9.0",
        "extended-properties:Company": "BroadOn Communications ",
        "extended-properties:Template": "Normal.dot",
        "meta:author": " Andy Chan",
        "meta:character-count": "1671",
        "meta:creation-date": "2006-08-10T06:13:00Z",
        "meta:keyword": "",
        "meta:last-author": "Paul Mielke",
        "meta:page-count": "1",
        "meta:print-date": "2005-12-08T02:06:00Z",
        "meta:save-date": "2006-08-10T06:42:00Z",
        "meta:word-count": "293",
        "modified": "2006-08-10T06:42:00Z",
        "resourceName": "b'ds_netcard_20060809_1.doc'",
        "subject": "",
        "title": "System Boot on NC",
        "w:comments": "",
        "xmpTPg:NPages": "1"
    }
}