{
    "XSDTerm.html": {
        "modified": "2005-07-07 02:05:04",
        "size": "19.48KB",
        "md5": "9b702c6e3ecaa36276c19272ceccba23",
        "sha256": "3bdf5d2f59dedaacd576bd4f74f83ac19f977fb8248a8ed3b46e71a9f214b01e"
    },
    "Metadata": {
        "Content-Encoding": "UTF-8",
        "Content-Type": "text/html; charset=UTF-8",
        "Content-Type-Hint": "text/html; charset=UTF-8",
        "X-Parsed-By": [
            "org.apache.tika.parser.DefaultParser",
            "org.apache.tika.parser.html.HtmlParser"
        ],
        "X-TIKA:content_handler": "ToTextContentHandler",
        "X-TIKA:embedded_depth": "0",
        "X-TIKA:parse_time_millis": "2",
        "dc:title": "Uses of Interface org.eclipse.xsd.XSDTerm (XSD Javadoc)",
        "resourceName": "b'XSDTerm.html'",
        "title": "Uses of Interface org.eclipse.xsd.XSDTerm (XSD Javadoc)"
    }
}