{
    "nms_top_16x32.v": {
        "modified": "2020-10-06 13:42:02.078685",
        "size": "6.07KB",
        "md5": "6e63f9f97ffc66119f43b65e9a47bc81",
        "sha256": "17609ee2795c437ceb517f601acb458e699b1c3b376d9acc223d584cddd7e50e"
    },
    "Metadata": {
        "Content-Encoding": "ISO-8859-1",
        "Content-Type": "text/plain; charset=ISO-8859-1",
        "X-Parsed-By": [
            "org.apache.tika.parser.DefaultParser",
            "org.apache.tika.parser.csv.TextAndCSVParser"
        ],
        "X-TIKA:content_handler": "ToTextContentHandler",
        "X-TIKA:embedded_depth": "0",
        "X-TIKA:parse_time_millis": "1",
        "resourceName": "b'nms_top_16x32.v'"
    }
}